ccs_digitalmarketplace_test_utils-7.7.0.dist-info/licenses/LICENCE
dmtestutils/__init__.py
dmtestutils/comparisons.py
dmtestutils/fixtures.py
dmtestutils/frontend.py
dmtestutils/login.py
dmtestutils/mocking.py
dmtestutils/api_model_stubs/__init__.py
dmtestutils/api_model_stubs/audit_event.py
dmtestutils/api_model_stubs/base.py
dmtestutils/api_model_stubs/brief.py
dmtestutils/api_model_stubs/brief_response.py
dmtestutils/api_model_stubs/communication.py
dmtestutils/api_model_stubs/framework.py
dmtestutils/api_model_stubs/framework_agreement.py
dmtestutils/api_model_stubs/lot.py
dmtestutils/api_model_stubs/lot_pricing.py
dmtestutils/api_model_stubs/lot_questions_response.py
dmtestutils/api_model_stubs/services.py
dmtestutils/api_model_stubs/supplier.py
dmtestutils/api_model_stubs/supplier_framework.py
dmtestutils/api_model_stubs/technical_ability_certificate.py
ccs_digitalmarketplace_test_utils-7.7.0.dist-info/METADATA
ccs_digitalmarketplace_test_utils-7.7.0.dist-info/WHEEL
ccs_digitalmarketplace_test_utils-7.7.0.dist-info/top_level.txt
ccs_digitalmarketplace_test_utils-7.7.0.dist-info/RECORD
