Metadata-Version: 2.4
Name: ccs-digitalmarketplace-test-utils
Version: 7.7.0
Summary: Utilities for testing Digital Marketplace apps.
Author: GDS Developers, CCS Developers
Project-URL: Homepage, https://github.com/Crown-Commercial-Service/ccs-digitalmarketplace-test-utils
Project-URL: Repository, https://github.com/Crown-Commercial-Service/ccs-digitalmarketplace-test-utils.git
Project-URL: Issues, https://github.com/Crown-Commercial-Service/ccs-digitalmarketplace-test-utils/issues
Project-URL: Changelog, https://github.com/Crown-Commercial-Service/ccs-digitalmarketplace-test-utils/CHANGELOG.md
Requires-Python: <3.15,>=3.11
License-File: LICENCE
Provides-Extra: dev
Requires-Dist: flake8==7.3.0; extra == "dev"
Requires-Dist: black==25.12.0; extra == "dev"
Requires-Dist: pytest==9.0.2; extra == "dev"
Requires-Dist: filetype==1.2.0; extra == "dev"
Requires-Dist: pre-commit==4.5.1; extra == "dev"
Dynamic: license-file
